MANIFEST.in
README.rst
setup.cfg
setup.py
versioneer.py
docs/Makefile
docs/make.bat
docs/quickstart.md
docs/source/conf.py
docs/source/cublas.rst
docs/source/cuda-libs.rst
docs/source/cufft.rst
docs/source/curand.rst
docs/source/cusparse.rst
docs/source/env-variables.rst
docs/source/index.rst
docs/source/install.rst
docs/source/release-notes.rst
docs/source/sorting.rst
pyculib/__init__.py
pyculib/_version.py
pyculib/config.py
pyculib/nputil.py
pyculib/runtests.py
pyculib/warnings.py
pyculib.egg-info/PKG-INFO
pyculib.egg-info/SOURCES.txt
pyculib.egg-info/dependency_links.txt
pyculib.egg-info/top_level.txt
pyculib/blas/__init__.py
pyculib/blas/api.py
pyculib/blas/binding.py
pyculib/fft/__init__.py
pyculib/fft/api.py
pyculib/fft/binding.py
pyculib/rand/__init__.py
pyculib/rand/api.py
pyculib/rand/binding.py
pyculib/sorting/__init__.py
pyculib/sorting/common.py
pyculib/sorting/radixsort.py
pyculib/sorting/segsort.py
pyculib/sparse/__init__.py
pyculib/sparse/api.py
pyculib/sparse/binding.py
pyculib/sparse/decls.py
pyculib/tests/__init__.py
pyculib/tests/base.py
pyculib/tests/blas.py
pyculib/tests/test_blas.py
pyculib/tests/test_blas_low_level.py
pyculib/tests/test_fft.py
pyculib/tests/test_rand.py
pyculib/tests/test_sorting.py
pyculib/tests/test_sparse.py
pyculib/utils/__init__.py
pyculib/utils/cctypes.py
pyculib/utils/finalizer.py
pyculib/utils/libutils.py