Metadata-Version: 1.0
Name: pyculib
Version: 1.0.1
Summary: Pyculib - python bindings for NVIDIA CUDA libraries
Home-page: http://continuum.io
Author: Continuum Analytics, Inc.
Author-email: support@continuum.io
License: BSD
Platform: UNKNOWN
